rechunkit/__init__.py
rechunkit/main.py
rechunkit-0.1.2.dist-info/METADATA
rechunkit-0.1.2.dist-info/WHEEL
rechunkit-0.1.2.dist-info/licenses/LICENSE
rechunkit-0.1.2.dist-info/RECORD
