Metadata-Version: 2.4
Name: rechunkit
Version: 0.1.2
Summary: Functions to efficiently rechunk multidimensional arrays
Project-URL: Documentation, https://mullenkamp.github.io/rechunkit/
Project-URL: Source, https://github.com/mullenkamp/rechunkit
Author-email: mullenkamp <mullenkamp1@gmail.com>
License-File: LICENSE
Classifier: Programming Language :: Python :: 3 :: Only
Requires-Python: >=3.9
Requires-Dist: numpy>=1.26
